{"slug": "a-tea-party", "title": "A Tea Party", "author": "DLM", "pages": [{"text": "A Tea Party", "url": "/cache/images/16/3255819116_9475547a40.jpg", "width": 75, "height": 100}, {"text": "Having a tea party is fun.", "url": "/cache/images/16/3255819116_9475547a40.jpg", "width": 375, "height": 500}, {"text": "First, make a list of friends.", "url": "/cache/images/85/6783298985_73b566a57e.jpg", "width": 500, "height": 290}, {"text": "List some of your favorite friends.", "url": "/cache/images/76/3293117576_05f43d8305.jpg", "width": 500, "height": 332}, {"text": "Next, make cards to tell your friends about the party.", "url": "/cache/images/35/5640463235_747b69ca3e.jpg", "width": 500, "height": 281}, {"text": "You can make plain cards.", "url": "/cache/images/27/4010252027_c40bcc6f1f.jpg", "width": 500, "height": 346}, {"text": "You can make colorful cards.", "url": "/cache/images/44/3744038544_aa7a36398a.jpg", "width": 500, "height": 499}, {"text": "Then, get ready for the tea party.", "url": "/cache/images/75/3254988475_ac24c1c05b.jpg", "width": 500, "height": 375}, {"text": "You need cups for the tea.", "url": "/cache/images/15/3141325415_92690ed008.jpg", "width": 333, "height": 500}, {"text": "You need plates for cake.", "url": "/cache/images/30/8017187830_45510502d6.jpg", "width": 497, "height": 500}, {"text": "You need forks to eat the cake.", "url": "/cache/images/65/925294465_4d5f4b3c1b.jpg", "width": 500, "height": 275}, {"text": "Then, find some flowers.", "url": "/cache/images/00/5484827300_5720729cfa.jpg", "width": 333, "height": 500}, {"text": "The flowers make your tea party special.", "url": "/cache/images/26/418180326_f27f5fe13d.jpg", "width": 415, "height": 500}, {"text": "Finally, wait for your friends to arrive.", "url": "/cache/images/74/12610853074_f065b1c1ba.jpg", "width": 500, "height": 334}, {"text": "Everyone likes a tea party.", "url": "/cache/images/16/3255819116_9475547a40.jpg", "width": 375, "height": 500}], "sheet": "4th Grade", "readings": [{"responses": ["do", "get", "it", "like", "look", "make", "put", "want"], "comments": ["", "Want to go!", "Make it", "Do it", "Make it", "Like it?", "I like!", "Looks good", "Get some", "Put on", "Get some", "I like!", "You like?", "All here!", "I like!"]}, {"responses": ["different", "get", "good", "like", "look", "make", "some", "that"], "comments": ["", "Looks good!", "Who? ", "Make it", "Get some", "Can make", "That is good!", "That is good!", "Some more", "Get some", "Different", "Get some", "Different", "Look good!", "You like?"]}, {"responses": ["do", "get", "good", "help", "it", "make", "put", "want"], "comments": ["", "I like.", "I can do it.", "Who?", "Make some", "Want different", "Make more", "Can help", "Get it", "I want", "Put on", "That is good!", "Want more", "More", "That is good!"]}]}