{"slug": "gifts-from-grandma", "title": "Gifts from Grandma", "author": "DLM", "pages": [{"text": "Gifts from Grandma", "url": "/cache/images/68/6022973168_466b3fd59a.jpg", "width": 100, "height": 67}, {"text": "Gifts from Grandma", "url": "/cache/images/68/6022973168_466b3fd59a.jpg", "width": 500, "height": 334}, {"text": "Mary was a little girl. Mary lived with Uncle Craven.", "url": "/cache/images/09/3547675609_d5d4841c92.jpg", "width": 332, "height": 500}, {"text": "Mary's Grandma wanted to send gifts to Mary. Grandma wanted to mail the gifts to Uncle Craven's house.", "url": "/cache/images/68/6022973168_466b3fd59a.jpg", "width": 500, "height": 334}, {"text": "Grandma went to the toy store.", "url": "/cache/images/40/3943368940_f80e017184.jpg", "width": 375, "height": 500}, {"text": "Grandma found many toys at the toy store.", "url": "/cache/images/15/6002411615_856035378c.jpg", "width": 331, "height": 500}, {"text": "Grandma looked at all the toys.", "url": "/cache/images/04/3476254904_83106a4457.jpg", "width": 500, "height": 375}, {"text": "The toy store had soft teddy bears.", "url": "/cache/images/74/8324405674_f75e35cbe0.jpg", "width": 500, "height": 333}, {"text": "The toy store had hard blocks.", "url": "/cache/images/56/4666856356_ccc35bcbf9.jpg", "width": 500, "height": 333}, {"text": "The toy store had smooth robots.", "url": "/cache/images/73/582581373_0607689dde.jpg", "width": 333, "height": 500}, {"text": "Grandma took the toys to the cashier.", "url": "/cache/images/42/91875542_24f9fdbfaf.jpg", "width": 500, "height": 375}, {"text": "Grandma gave the cashier money.", "url": "/cache/images/28/4946929028_8c37a41325.jpg", "width": 333, "height": 500}, {"text": "The cashier put the toys in boxes.", "url": "/cache/images/64/73402664_fa585db1d0.jpg", "width": 333, "height": 500}, {"text": "Grandma mailed the toys to Mary. Grandma put some books in the mail for Mary, too.", "url": "/cache/images/70/2165146570_6bafcd7312.jpg", "width": 333, "height": 500}, {"text": "The toys and books arrived for Mary in the mail.", "url": "/cache/images/09/3547675609_d5d4841c92.jpg", "width": 332, "height": 500}, {"text": "Mary read the big books.", "url": "/cache/images/82/5076790282_17c4215a10.jpg", "width": 500, "height": 177}, {"text": "Mary read the small books.", "url": "/cache/images/06/11367480906_7fb5c2306d.jpg", "width": 500, "height": 315}, {"text": "Mary played with the toys.", "url": "/cache/images/89/3547676189_a8d2c850de.jpg", "width": 332, "height": 500}, {"text": "Mary played with shiny balls.", "url": "/cache/images/68/52275668_4fb50ab4ef.jpg", "width": 500, "height": 376}, {"text": "Mary had fun playing with the toys.", "url": "/cache/images/83/3547675983_dcc1c93f67.jpg", "width": 332, "height": 500}, {"text": "Mary liked the gifts. Grandma was happy.", "url": "/cache/images/68/6022973168_466b3fd59a.jpg", "width": 500, "height": 334}], "sheet": "5th Grade", "readings": [{"responses": ["different", "get", "go", "like", "more", "open", "put", "some", "want"], "comments": ["", "Look here!", "Look!", "She wants.", "She goes.", "Some toys", "More", "Looks good!", "More", "It goes!", "Put here", "Get it.", "Put it in.", "Open it.", "She wants.", "Open", "More", "She likes.", "Different", "She likes.", "She likes."]}, {"responses": ["different", "get", "go", "good", "here", "more", "put", "turn", "want"], "comments": ["", "She is good.", "She is here.", "Wants to do", "Goes here.", "More!", "Can get some", "Put on", "Different", "Go and stop", "Gets them.", "Put it in.", "Looks good!", "Put in", "She gets them.", "Open it up", "Different", "She turns", "Some", "Different", "She goes up"]}, {"responses": ["go", "here", "like", "look", "more", "on", "open"], "comments": ["", "Here she is.", "Sit here.", "Like to do it", "She goes here.", "Do you like?", "She looks.", "He has it on.", "Some more", "Can go", "Want to get them", "Here you go!", "Open", "Put them in", "She likes!", "Look in", "Open it", "She looks good!", "More", "Some more", "Looks good!"]}]}