{"slug": "roys-new-school", "title": "Roy's New School", "author": "DLM", "pages": [{"text": "Roy's New School", "url": "/cache/images/58/6958984058_3dfd584d54.jpg", "width": 66, "height": 100}, {"text": "Roy was a young boy.", "url": "/cache/images/58/6958984058_3dfd584d54.jpg", "width": 331, "height": 500}, {"text": "Roy moved to Florida with his family.", "url": "/cache/images/37/4725356637_94d96d969f.jpg", "width": 500, "height": 333}, {"text": "Roy had to go to a new school.", "url": "/cache/images/94/5520026094_eb40cf4b79.jpg", "width": 500, "height": 375}, {"text": "Roy missed his old school. Roy missed his old friends.", "url": "/cache/images/85/9533783485_ebb08f1aeb.jpg", "width": 500, "height": 443}, {"text": "When Roy got to his new school, he put his bag in his locker.", "url": "/cache/images/21/6928488821_0d8033b642.jpg", "width": 500, "height": 353}, {"text": "Then, Roy went to his new classroom.", "url": "/cache/images/83/3509154283_861cdeafcf.jpg", "width": 500, "height": 333}, {"text": "Roy learned many things at his new school.", "url": "/cache/images/21/6928488821_0d8033b642.jpg", "width": 500, "height": 353}, {"text": "Roy learned things from his new teacher.", "url": "/cache/images/79/8243793379_d8bbf4f46e.jpg", "width": 500, "height": 333}, {"text": "Roy learned things from his new principal.", "url": "/cache/images/94/7795787694_e0aa036d94.jpg", "width": 500, "height": 333}, {"text": "Roy learned things when his new class went outside.", "url": "/cache/images/91/4275879491_6332ac1550.jpg", "width": 335, "height": 500}, {"text": "Roy learned about nature when his class was outside.", "url": "/cache/images/31/648711831_515ae61f3f.jpg", "width": 500, "height": 333}, {"text": "Roy learned things when his new class went to the library.", "url": "/cache/images/48/4385738848_472d35d4c7.jpg", "width": 500, "height": 333}, {"text": "Roy learned about comic books when his class was at the library.", "url": "/cache/images/13/12245978213_601a83ee46.jpg", "width": 500, "height": 332}, {"text": "Roy sat with new students when his class went to lunch.", "url": "/cache/images/59/6214619159_1361178fce.jpg", "width": 500, "height": 333}, {"text": "Roy made new friends at his new school.", "url": "/cache/images/64/8720604364_85c5931a14.jpg", "width": 500, "height": 333}, {"text": "Roy liked his new school.", "url": "/cache/images/94/5520026094_eb40cf4b79.jpg", "width": 500, "height": 375}], "sheet": "8th Grade", "readings": [{"responses": ["different", "go", "good", "he", "like", "not", "put", "you"], "comments": ["", "Here he is.", "They go", "Different ", "Not the same", "Put in", "Go", "Different ", "Different ", "Different ", "They go", "They go", "You go here.", "He like it.", "He like it.", "Different ", "Good"]}, {"responses": ["he", "here", "like", "look", "more", "not", "put", "you"], "comments": ["", "Look", "Go here", "Not the same", "Not good", "He put in", "Go here", "Not the same", "Not the same", "Not the same", "He learned more", "He learned more", "In here", "He liked that.", "He liked that.", "Not the same", "Do you like it?"]}, {"responses": ["different", "go", "good", "here", "more", "on", "put", "you"], "comments": ["", "On a bike", "Here", "It was different.", "Different here", "Put it in.", "Go in", "Like you", "Like you", "Do you?", "Go outside", "Go outside", "You do that.", "It was good.", "It was good.", "More friends", "It was good."]}]}