{"slug": "the-first-day-of-school-2", "title": "The First Day of School", "author": "DLM", "pages": [{"text": "The First Day of School", "url": "/cache/images/91/3176885291_dd531a44d3.jpg", "width": 100, "height": 67}, {"text": "It was the first day of school.", "url": "/cache/images/91/3176885291_dd531a44d3.jpg", "width": 500, "height": 334}, {"text": "Jan was excited to go to school.", "url": "/cache/images/81/5298344981_af164529ab.jpg", "width": 500, "height": 484}, {"text": "Jan packed her backpack for school.", "url": "/cache/images/43/1365822143_35204f50fd.jpg", "width": 427, "height": 500}, {"text": "Jan put pencils in the backpack.", "url": "/cache/images/55/484601255_bf79ebc82d.jpg", "width": 375, "height": 500}, {"text": "Jan put erasers in the backpack.", "url": "/cache/images/88/249321288_6abbb00343.jpg", "width": 500, "height": 333}, {"text": "Jan put a notebook in the backpack.", "url": "/cache/images/98/143995198_a2df8884b6.jpg", "width": 489, "height": 500}, {"text": "Jan put glue in the backpack.", "url": "/cache/images/92/2927809892_083ecf4be2.jpg", "width": 375, "height": 500}, {"text": "Jan put crayons in the backpack.", "url": "/cache/images/99/404298099_c60259d30a.jpg", "width": 500, "height": 375}, {"text": "Jan put markers in the backpack.", "url": "/cache/images/39/8180199239_7accdbf3e4.jpg", "width": 375, "height": 500}, {"text": "Jan put tissues in the backpack.", "url": "/cache/images/70/2380151170_77798b7452.jpg", "width": 500, "height": 375}, {"text": "Jan was ready for school.", "url": "/cache/images/81/5298344981_af164529ab.jpg", "width": 500, "height": 484}], "sheet": "4th Grade", "readings": [{"responses": ["different", "get", "go", "here", "make", "more", "put", "same", "she"], "comments": ["", "Get on.", "She goes.", "Put on.", "Same.", "More", "Here", "Make it.", "Different!", "All different.", "Get some", "Go"]}, {"responses": ["finished", "get", "go", "like", "look", "open", "put", "she"], "comments": ["", "They go.", "She wants to go.", "Put in", "Get some", "Get some ", "Open it", "Put on", "I like!", "Put in", "Look here", "Finished"]}, {"responses": ["get", "go", "help", "like", "open", "put", "some"], "comments": ["", "Go in here", "Looks good.", "Can open", "Put in", "Put in", "Get it", "Get some", "You like?", "Get some", "Help", "All finished"]}]}